django_pell/__init__.py
django_pell/apps.py
django_pell/fields.py
django_pell/widgets.py
django_pell/static/django_pell/css/pell.min.css
django_pell/static/django_pell/js/pell.min.js
django_pell/templates/django_pell/pell.html
django_pell/templates/django_pell/widget.js
django_pell-0.0.10.dist-info/LICENSE
django_pell-0.0.10.dist-info/METADATA
django_pell-0.0.10.dist-info/WHEEL
django_pell-0.0.10.dist-info/top_level.txt
django_pell-0.0.10.dist-info/RECORD
