Metadata-Version: 2.1
Name: django-pell
Version: 0.0.10
Summary: Django pell WYSIWYG widget
Home-page: https://gitlab.com/BradleyKirton/django-pell/
Author: Bradley Stuart Kirton
Author-email: bradleykirton@gmail.com
License: MIT
Keywords: django
Platform: UNKNOWN
Classifier: Intended Audience :: Developers
Classifier: License :: OSI Approved :: MIT License
Classifier: Programming Language :: Python :: 3.6
Classifier: Operating System :: OS Independent
Classifier: Topic :: Software Development :: Libraries
Classifier: Topic :: Utilities
Classifier: Environment :: Web Environment
Classifier: Framework :: Django
Classifier: Framework :: Django :: 2.1
Classifier: Programming Language :: Python :: 3
Classifier: Programming Language :: Python :: 3.6
Requires-Dist: django
Provides-Extra: dev
Requires-Dist: pytest ; extra == 'dev'
Requires-Dist: pytest-cov ; extra == 'dev'
Requires-Dist: pytest-sugar ; extra == 'dev'
Requires-Dist: django-coverage-plugin ; extra == 'dev'
Requires-Dist: pytest-django ; extra == 'dev'
Requires-Dist: bumpversion ; extra == 'dev'
Requires-Dist: twine ; extra == 'dev'
